README.rst
setup.py
tomler/__init__.py
tomler.egg-info/PKG-INFO
tomler.egg-info/SOURCES.txt
tomler.egg-info/dependency_links.txt
tomler.egg-info/requires.txt
tomler.egg-info/top_level.txt