Metadata-Version: 2.1
Name: tomler
Version: 0.1.3
Summary: A simple reader for TOML configuration files.
Home-page: https://github.com/DrugoLebowski/tomler
Author: Valerio Belli
Author-email: belli.valerio@gmail.com
License: MIT
Platform: UNKNOWN
Classifier: License :: OSI Approved :: MIT License
Classifier: Programming Language :: Python
Classifier: Programming Language :: Python :: 3
Classifier: Programming Language :: Python :: 3.5
Classifier: Programming Language :: Python :: Implementation :: CPython
Classifier: Programming Language :: Python :: Implementation :: PyPy
Requires-Python: >=3.5
